LICENSE
README.md
pyproject.toml
src/riceinfo/__init__.py
src/riceinfo/__main__.py
src/riceinfo/rice.py
src/riceinfo.egg-info/PKG-INFO
src/riceinfo.egg-info/SOURCES.txt
src/riceinfo.egg-info/dependency_links.txt
src/riceinfo.egg-info/entry_points.txt
src/riceinfo.egg-info/requires.txt
src/riceinfo.egg-info/top_level.txt
tests/test_draw_rice.py
tests/test_riceCountry.py
tests/test_ricehistory.py
tests/test_tellPun_rice.py