Metadata-Version: 2.1
Name: riceinfo
Version: 0.1.0
Summary: A fun package for your rice needs. Print out riceballs, rice puns, rice history, and country's main rice types!
Author-email: Kei Oshima <ko2091@nyu.edu>, Ryan Horng <rh3025@nyu.edu>, Andrew Huang <ah5360@nyu.edu>, Richard Qu <rq2014@nyu.edu>
License: MIT License
Project-URL: Homepage, https://github.com/software-students-fall2023/3-python-package-exercise-riceballz
Project-URL: Repository, https://github.com/software-students-fall2023/3-python-package-exercise-riceballz.git
Project-URL: Bug Tracker, https://github.com/software-students-fall2023/3-python-package-exercise-riceballz/issues
Keywords: python,package,build,rice,history,pun,ascii
Classifier: Programming Language :: Python :: 3
Classifier: Intended Audience :: Education
Classifier: License :: OSI Approved :: GNU General Public License v3 (GPLv3)
Classifier: Operating System :: OS Independent
Requires-Python: >=3.7
License-File: LICENSE
Provides-Extra: dev
Requires-Dist: pytest; extra == "dev"
